{
	"image": "DADDY_DEAREST",
	"pos": [0, 0],

	"singDuration": 6,
	"color": "0xFFAF66CE",

	"anims": [
		{"anim": "idle",  "name": "idle",  "fps": 24, "loop": false, "offsets": [0,   0]},
		{"anim": "left",  "name": "left",  "fps": 24, "loop": false, "offsets": [-9, 10]},
		{"anim": "down",  "name": "down",  "fps": 24, "loop": false, "offsets": [0, -30]},
		{"anim": "up",    "name": "up",    "fps": 24, "loop": false, "offsets": [-6, 50]},
		{"anim": "right", "name": "right", "fps": 24, "loop": false, "offsets": [0,  27]}
	]
}